cgpcnn/algorithm/__init__.py
cgpcnn/algorithm/cgp.py
cgpcnn/algorithm/cgp_config.py
cgpcnn/algorithm/individual.py
cgpcnn/basic_models/__init__.py
cgpcnn/basic_models/cnn_model.py
cgpcnn/basic_models/gcn_model.py
cgpcnn/blocks/__init__.py
cgpcnn/blocks/cnn_blocks.py
cgpcnn/blocks/cnn_init_weights.py
cgpcnn/blocks/gcn_blocks.py
cgpcnn/converters/__init__.py
cgpcnn/converters/cgp2cnn.py
cgpcnn/converters/cgp2gcn.py
cgpcnn/evolutions/__init__.py
cgpcnn/evolutions/cnn_evolution.py
cgpcnn/evolutions/gcn_evolution.py
cgpcnn/evolutions/parallel_evaluation.py
cgpcnn/loaders/__init__.py
cgpcnn/loaders/cifar10_loader.py
cgpcnn/loaders/cora_loader.py
cgpcnn/loaders/image_net_loader.py
cgpcnn/loaders/loader_base.py
cgpcnn/loaders/mnist_loader.py
cgpcnn/trainers/__init__.py
cgpcnn/trainers/cnn_trainer.py
cgpcnn/trainers/gcn_trainer.py
cgpcnn/trainers/trainer_base.py
cgpcnn/utils/__init__.py
cgpcnn/utils/image_net_scraper.py
cgpcnn/utils/logger.py
cgpcnn/utils/plotting.py
cgpcnn/utils/set_seed.py
cgpcnn/utils/singleton.py
cgpcnn-0.1.2.dist-info/LICENSE
cgpcnn-0.1.2.dist-info/METADATA
cgpcnn-0.1.2.dist-info/WHEEL
cgpcnn-0.1.2.dist-info/top_level.txt
cgpcnn-0.1.2.dist-info/RECORD
