Metadata-Version: 2.1
Name: cgpcnn
Version: 0.1.2
Summary: A project featuring methods for optimizing neural networks using PyTorch.
Home-page: https://github.com/MrLipa/CGP-CNN-Optimizer
Author: Tomasz Szkaradek
Author-email: bilbo.weirdo@gmail.com
License: MIT
Classifier: License :: OSI Approved :: MIT License
Classifier: Programming Language :: Python :: 3.10
Classifier: Operating System :: OS Independent
Requires-Python: >=3.10.14
License-File: LICENSE
Requires-Dist: torch
Requires-Dist: torchvision
Requires-Dist: torchaudio
Requires-Dist: matplotlib
Requires-Dist: seaborn
Requires-Dist: scikit-learn
Requires-Dist: pandas
Requires-Dist: requests
Requires-Dist: mlflow
Requires-Dist: pydot
Requires-Dist: torchsummary
Requires-Dist: torch-geometric
Provides-Extra: all
Requires-Dist: torch ; extra == 'all'
Requires-Dist: torchvision ; extra == 'all'
Requires-Dist: torchaudio ; extra == 'all'
Requires-Dist: matplotlib ; extra == 'all'
Requires-Dist: seaborn ; extra == 'all'
Requires-Dist: scikit-learn ; extra == 'all'
Requires-Dist: pandas ; extra == 'all'
Requires-Dist: torchsummary ; extra == 'all'
Requires-Dist: python-dotenv ; extra == 'all'
Requires-Dist: click ; extra == 'all'
Requires-Dist: coverage ; extra == 'all'
Requires-Dist: myst-parser ; extra == 'all'
Requires-Dist: flake8 ; extra == 'all'
Requires-Dist: wheel ; extra == 'all'
Requires-Dist: ipykernel ; extra == 'all'
Requires-Dist: mlflow ; extra == 'all'
Requires-Dist: Sphinx ; extra == 'all'
Requires-Dist: sphinx-rtd-theme ; extra == 'all'
Requires-Dist: twine ; extra == 'all'
Requires-Dist: requests ; extra == 'all'
Requires-Dist: pydot ; extra == 'all'
Provides-Extra: basic
Requires-Dist: torch ; extra == 'basic'
Requires-Dist: torchvision ; extra == 'basic'
Requires-Dist: torchaudio ; extra == 'basic'
Requires-Dist: matplotlib ; extra == 'basic'
Requires-Dist: seaborn ; extra == 'basic'
Requires-Dist: scikit-learn ; extra == 'basic'
Requires-Dist: pandas ; extra == 'basic'
Requires-Dist: requests ; extra == 'basic'
Requires-Dist: mlflow ; extra == 'basic'
Requires-Dist: pydot ; extra == 'basic'
Requires-Dist: torchsummary ; extra == 'basic'
Provides-Extra: dev
Requires-Dist: python-dotenv ; extra == 'dev'
Requires-Dist: click ; extra == 'dev'
Requires-Dist: coverage ; extra == 'dev'
Requires-Dist: flake8 ; extra == 'dev'
Requires-Dist: wheel ; extra == 'dev'
Requires-Dist: ipykernel ; extra == 'dev'
Requires-Dist: twine ; extra == 'dev'
Provides-Extra: doc
Requires-Dist: Sphinx ; extra == 'doc'
Requires-Dist: sphinx-rtd-theme ; extra == 'doc'
Requires-Dist: myst-parser ; extra == 'doc'
